Metadata-Version: 2.1
Name: pyRXG
Version: 1.0.0
Summary: Regular Expression Generator and Generaliser
Home-page: https://wxwilcke.gitlab.io/pyRXG
Download-URL: https://gitlab.com/wxwilcke/pyRXG/-/archive/1.0.0/pyRXG-1.0.0.tar.gz
Author: Xander Wilcke
Author-email: Xander Wilcke <w.x.wilcke@vu.nl>
License:                     GNU GENERAL PUBLIC LICENSE
Project-URL: Homepage, https://wxwilcke.gitlab.io/pyRXG
Project-URL: Bug Tracker, https://gitlab.com/wxwilcke/pyRXG/-/issues
Keywords: regex,regular expression,text processing,generator,clustering
Classifier: Programming Language :: Python :: 3
Classifier: License :: OSI Approved :: GNU General Public License v3 (GPLv3)
Classifier: Operating System :: OS Independent
Requires-Python: >=3.8
License-File: LICENSE
Requires-Dist: numpy
